main.py
thinkingface-0.1.0.dev1.dist-info/LICENSE
thinkingface-0.1.0.dev1.dist-info/METADATA
thinkingface-0.1.0.dev1.dist-info/WHEEL
thinkingface-0.1.0.dev1.dist-info/entry_points.txt
thinkingface-0.1.0.dev1.dist-info/top_level.txt
thinkingface-0.1.0.dev1.dist-info/RECORD
