Metadata-Version: 2.1
Name: thinkingface
Version: 0.1.0.dev1
Summary: A programming assistant
Project-URL: Homepage, https://github.com/thinkingfaceco/thinkingface
Classifier: Programming Language :: Python :: 3
Classifier: License :: OSI Approved :: Apache Software License
Classifier: Operating System :: OS Independent
Requires-Python: >=3.8
License-File: LICENSE
Requires-Dist: textual >=0.34
